LICENSE
README.md
setup.py
random_user_agent/__init__.py
random_user_agent/params.py
random_user_agent/user_agent.py
random_user_agent/data/user_agents.zip
solotop_random_user_agent.egg-info/PKG-INFO
solotop_random_user_agent.egg-info/SOURCES.txt
solotop_random_user_agent.egg-info/dependency_links.txt
solotop_random_user_agent.egg-info/top_level.txt