Metadata-Version: 2.1
Name: solotop-random-user-agent
Version: 0.69.1
Summary: A package to get random user agents based filters provided by user
Home-page: https://github.com/solotop999/solotop_random_user_agent
Author: solotop999
Author-email: zororoaz01@gmail.com
License: MIT
Classifier: Programming Language :: Python :: 3
Classifier: License :: OSI Approved :: MIT License
Classifier: Operating System :: OS Independent
License-File: LICENSE
